ARBOLpy/ARBOL.py
ARBOLpy/__init__.py
ARBOLpy-0.0.9.dist-info/LICENSE
ARBOLpy-0.0.9.dist-info/METADATA
ARBOLpy-0.0.9.dist-info/WHEEL
ARBOLpy-0.0.9.dist-info/top_level.txt
ARBOLpy-0.0.9.dist-info/RECORD
