Metadata-Version: 2.1
Name: ARBOLpy
Version: 0.0.9
Summary: python implementation of ARBOL scRNAseq iterative tiered clustering
Home-page: https://github.com/jo-m-lab/ARBOLpy
Author: Kyle Kimler, Ruben van Esch
Author-email: kkimler@broadinstitute.org
Project-URL: Bug Tracker, https://github.com/jo-m-lab/ARBOLpy/issues
Project-URL: Source code, https://github.com/jo-m-lab/ARBOLpy
Classifier: Programming Language :: Python :: 3
Classifier: License :: OSI Approved :: MIT License
Classifier: Operating System :: OS Independent
Requires-Python: >=3.8
License-File: LICENSE
Requires-Dist: scanpy (>=1.9.0)
Requires-Dist: anytree (>=2.8.0)
Requires-Dist: pandas (>=1.0.5)
Requires-Dist: numpy (>=1.18.5)
Requires-Dist: matplotlib (>=3.5.1)
Requires-Dist: scipy (>=1.4.1)
Requires-Dist: leidenalg (>=0.8)
